drf_composable_permissions/__init__.py
drf_composable_permissions/p.py
drf_composable_permissions/permissions.py
drf_composable_permissions-0.1.1.dist-info/DESCRIPTION.rst
drf_composable_permissions-0.1.1.dist-info/METADATA
drf_composable_permissions-0.1.1.dist-info/RECORD
drf_composable_permissions-0.1.1.dist-info/WHEEL
drf_composable_permissions-0.1.1.dist-info/metadata.json
drf_composable_permissions-0.1.1.dist-info/top_level.txt
